scr/pygameMax/__init__.py
scr/pygameMax/pac.py
scr/pygameMax/infodata/basicHelp.txt
scr/pygameMax/infodata/overveiw
pygamemax-1.2.0.dist-info/METADATA
pygamemax-1.2.0.dist-info/WHEEL
pygamemax-1.2.0.dist-info/licenses/LICENCE
pygamemax-1.2.0.dist-info/RECORD
