Metadata-Version: 2.3
Name: pygameMax
Version: 1.2.0
Summary: please email for any issues. Thanks :/
Author-email: Sam Fertig <sfertig007@gmail.com>
License-File: LICENCE
Classifier: License :: OSI Approved :: MIT License
Classifier: Operating System :: OS Independent
Classifier: Programming Language :: Python :: 3
Requires-Python: >=3.8
